gribnormalize
