Metadata-Version: 1.0
Name: gribnormalize
Version: 0.0.3dev
Summary: Utility functions for handling grib2s
Home-page: https://github.com/mapbox/grib-normalizer
Author: Damon Burgett
Author-email: damon@mapbox.com
License: MIT
Platform: UNKNOWN
